one_config/__init__.py
one_config/config.py
one_config-0.2.1.dist-info/LICENSE
one_config-0.2.1.dist-info/METADATA
one_config-0.2.1.dist-info/WHEEL
one_config-0.2.1.dist-info/top_level.txt
one_config-0.2.1.dist-info/RECORD
