Metadata-Version: 2.1
Name: one-config
Version: 0.2.1
Summary: A universally accessible config object that only has to be constructed once
Home-page: https://github.com/LiamConnell/one-config
Author: LiamConnell
License: MIT
Platform: UNKNOWN
Classifier: License :: OSI Approved :: MIT License
Classifier: Programming Language :: Python :: 3
Classifier: Programming Language :: Python :: 3.7
Requires-Dist: PyYAML
